bilibili/__init__.py
bilibili/bilibili.py
bilibili/config.py
bilibili-0.0.1.dist-info/DESCRIPTION.rst
bilibili-0.0.1.dist-info/METADATA
bilibili-0.0.1.dist-info/RECORD
bilibili-0.0.1.dist-info/WHEEL
bilibili-0.0.1.dist-info/entry_points.txt
bilibili-0.0.1.dist-info/metadata.json
bilibili-0.0.1.dist-info/top_level.txt
